snap_processor_bindings/__init__.py
snap_processor_bindings/model.py
eodc_faas_snap-2025.9.1.dist-info/METADATA
eodc_faas_snap-2025.9.1.dist-info/WHEEL
eodc_faas_snap-2025.9.1.dist-info/RECORD
