Metadata-Version: 2.1
Name: eodc-faas-snap
Version: 2025.9.1
Summary: Bindings for the snap processor exposed at EODC
Author: Lukas Weidenholzer
Author-email: lukas.weidenholzer@eodc.eu
Requires-Python: >=3.10,<3.13
Classifier: Programming Language :: Python :: 3
Classifier: Programming Language :: Python :: 3.10
Classifier: Programming Language :: Python :: 3.11
Requires-Dist: pydantic (>=2.0.1,<3.0.0)
